odoo/addons/l10n_ro_stock_picking_report/README.rst
odoo/addons/l10n_ro_stock_picking_report/__init__.py
odoo/addons/l10n_ro_stock_picking_report/__manifest__.py
odoo/addons/l10n_ro_stock_picking_report/models/__init__.py
odoo/addons/l10n_ro_stock_picking_report/models/stock_move_line.py
odoo/addons/l10n_ro_stock_picking_report/models/stock_picking.py
odoo/addons/l10n_ro_stock_picking_report/readme/CONTRIBUTORS.rst
odoo/addons/l10n_ro_stock_picking_report/readme/DESCRIPTION.rst
odoo/addons/l10n_ro_stock_picking_report/readme/INSTALL.rst
odoo/addons/l10n_ro_stock_picking_report/report/stock_picking_report_valued.xml
odoo/addons/l10n_ro_stock_picking_report/static/description/icon.png
odoo/addons/l10n_ro_stock_picking_report/static/description/icon.svg
odoo/addons/l10n_ro_stock_picking_report/static/description/index.html
odoo/addons/l10n_ro_stock_picking_report/tests/__init__.py
odoo/addons/l10n_ro_stock_picking_report/tests/common.py
odoo/addons/l10n_ro_stock_picking_report/tests/test_consum.py
odoo/addons/l10n_ro_stock_picking_report/tests/test_purchase_stock_picking_valued.py
odoo/addons/l10n_ro_stock_picking_report/tests/test_sale_stock_picking_valued.py
odoo14_addon_l10n_ro_stock_picking_report-14.0.0.1.0.dist-info/METADATA
odoo14_addon_l10n_ro_stock_picking_report-14.0.0.1.0.dist-info/WHEEL
odoo14_addon_l10n_ro_stock_picking_report-14.0.0.1.0.dist-info/top_level.txt
odoo14_addon_l10n_ro_stock_picking_report-14.0.0.1.0.dist-info/RECORD
